hathorlib/__init__.py
hathorlib/base_transaction.py
hathorlib/block.py
hathorlib/client.py
hathorlib/conf/__init__.py
hathorlib/conf/get_settings.py
hathorlib/conf/mainnet.py
hathorlib/conf/settings.py
hathorlib/conf/testnet.py
hathorlib/daa.py
hathorlib/exceptions.py
hathorlib/headers/__init__.py
hathorlib/headers/base.py
hathorlib/headers/deprecated_nano_header.py
hathorlib/headers/nano_header.py
hathorlib/headers/types.py
hathorlib/nanocontracts/__init__.py
hathorlib/nanocontracts/nanocontract.py
hathorlib/nanocontracts/on_chain_blueprint.py
hathorlib/nanocontracts/types.py
hathorlib/py.typed
hathorlib/scripts.py
hathorlib/serialization/__init__.py
hathorlib/serialization/adapters/__init__.py
hathorlib/serialization/adapters/generic_adapter.py
hathorlib/serialization/adapters/max_bytes.py
hathorlib/serialization/bytes_deserializer.py
hathorlib/serialization/bytes_serializer.py
hathorlib/serialization/deserializer.py
hathorlib/serialization/encoding/__init__.py
hathorlib/serialization/encoding/leb128.py
hathorlib/serialization/exceptions.py
hathorlib/serialization/serializer.py
hathorlib/serialization/types.py
hathorlib/token_creation_tx.py
hathorlib/transaction.py
hathorlib/utils.py
hathorlib/vertex_parser.py
hathorlib-0.11.0.dist-info/LICENSE.txt
hathorlib-0.11.0.dist-info/METADATA
hathorlib-0.11.0.dist-info/WHEEL
hathorlib-0.11.0.dist-info/RECORD
