Metadata-Version: 2.3
Name: hathorlib
Version: 0.11.0
Summary: Hathor Network base objects library
License: Apache-2.0
Author: Hathor Team
Author-email: contact@hathor.network
Requires-Python: >=3.9,<4
Classifier: License :: OSI Approved :: Apache Software License
Classifier: Operating System :: OS Independent
Classifier: Programming Language :: Python :: 3
Classifier: Programming Language :: Python :: 3.9
Classifier: Programming Language :: Python :: 3.10
Classifier: Programming Language :: Python :: 3.11
Classifier: Programming Language :: Python :: 3.12
Classifier: Programming Language :: Python :: 3.13
Classifier: Programming Language :: Python :: 3.6
Classifier: Programming Language :: Python :: 3.7
Classifier: Programming Language :: Python :: 3.8
Provides-Extra: client
Requires-Dist: aiohttp (>=3.9.3,<3.10.0) ; extra == "client"
Requires-Dist: base58 (>=2.1.1,<2.2.0)
Requires-Dist: cryptography (>=42.0.5,<42.1.0)
Requires-Dist: pycoin (>=0.92,<0.93)
Requires-Dist: structlog (>=22.3.0,<22.4.0) ; extra == "client"
Project-URL: Homepage, https://hathor.network/
Project-URL: Repository, https://github.com/HathorNetwork/python-hathorlib/
